able_labs_api/__init__.py
neon/__init__.py
neon/common/__init__.py
neon/common/constants.py
neon/common/enums.py
neon/common/path.py
neon/common/structs.py
neon/common/suitable/__init__.py
neon/common/suitable/constants.py
neon/common/suitable/enums.py
neon/common/suitable/struct.py
neon/utils/__init__.py
neon/utils/decorators.py
neon/utils/device_utils.py
neon/utils/dict_utils.py
neon/utils/enum_types.py
neon/utils/excel_utils.py
neon/utils/format_conversion.py
neon/utils/location_conversion.py
neon/utils/long_polling_getter.py
neon/utils/work_node.py
neon/utils/math/__init__.py
neon/utils/math/interpolator.py
neon/utils/math/linear_map.py
neon/utils/network/__init__.py
neon/utils/network/base_tcp.py
neon/utils/network/messenger.py
neon/utils/network/tcp_client.py
neon/utils/network/tcp_server.py
ABLE_Labs_API-0.0.2.dist-info/METADATA
ABLE_Labs_API-0.0.2.dist-info/WHEEL
ABLE_Labs_API-0.0.2.dist-info/top_level.txt
ABLE_Labs_API-0.0.2.dist-info/RECORD
