Metadata-Version: 2.1
Name: ABLE-Labs-API
Version: 0.0.2
Home-page: https://github.com/ABLE-Labs/ABLE-API
Author: sypark
Author-email: sy.park@ablelabsinc.com
Keywords: ablelabs
Classifier: Programming Language :: Python :: 3.10
Requires-Python: >=3.10
Requires-Dist: et-xmlfile >=1.1.0
Requires-Dist: future >=1.0.0
Requires-Dist: iso8601 >=2.1.0
Requires-Dist: loguru >=0.7.2
Requires-Dist: openpyxl >=3.1.5
Requires-Dist: pyserial >=3.5
Requires-Dist: PyYAML >=6.0.1
